cmconfig/__init__.py
cmconfig/__main__.py
cmconfig/bin/linux/blf_converter
cmconfig/bin/linux/blf_converter.exe
cmconfig/bin/linux/cmconfig
cmconfig/bin/linux/libSystem.IO.Ports.Native.so
cmconfig/bin/linux/libasc_reader.so
cmconfig/bin/linux/Schema/backend.schema.json
cmconfig/bin/linux/Schema/base.schema.json
cmconfig/bin/linux/Schema/bootloader.schema.json
cmconfig/bin/linux/Schema/classic_device_features.schema.json
cmconfig/bin/linux/Schema/classic_device_status.schema.json
cmconfig/bin/linux/Schema/license.schema.json
cmconfig/bin/linux/Schema/lldp.schema.json
cmconfig/bin/linux/Schema/modular_device_config.schema.json
cmconfig/bin/linux/Schema/modular_device_status.schema.json
cmconfig/bin/linux/Schema/topology.schema.json
cmconfig/bin/linux/x64/asc_reader.dll
cmconfig/bin/linux/x86/asc_reader.dll
cmconfig/bin/windows/aspnetcorev2_inprocess.dll
cmconfig/bin/windows/blf_converter
cmconfig/bin/windows/blf_converter.exe
cmconfig/bin/windows/cmconfig.exe
cmconfig/bin/windows/libasc_reader.so
cmconfig/bin/windows/Schema/backend.schema.json
cmconfig/bin/windows/Schema/base.schema.json
cmconfig/bin/windows/Schema/bootloader.schema.json
cmconfig/bin/windows/Schema/classic_device_features.schema.json
cmconfig/bin/windows/Schema/classic_device_status.schema.json
cmconfig/bin/windows/Schema/license.schema.json
cmconfig/bin/windows/Schema/lldp.schema.json
cmconfig/bin/windows/Schema/modular_device_config.schema.json
cmconfig/bin/windows/Schema/modular_device_status.schema.json
cmconfig/bin/windows/Schema/topology.schema.json
cmconfig/bin/windows/x64/asc_reader.dll
cmconfig/bin/windows/x86/asc_reader.dll
cmconfig-1.14.2.dist-info/METADATA
cmconfig-1.14.2.dist-info/WHEEL
cmconfig-1.14.2.dist-info/entry_points.txt
cmconfig-1.14.2.dist-info/top_level.txt
cmconfig-1.14.2.dist-info/RECORD
