Metadata-Version: 2.4
Name: cmconfig
Version: 1.14.2
Summary: Command line tool to control and configure Capture Modules
Author-email: Ayoub Kaanich <ayoub.kaanich@technica-engineering.de>
License: ## License Agreement
Requires-Python: >=3.9
